rendom/__init__.py
rendom-0.2.dist-info/METADATA
rendom-0.2.dist-info/WHEEL
rendom-0.2.dist-info/top_level.txt
rendom-0.2.dist-info/RECORD
